kbfi/__init__.py
kbfi/kbfi.py
kbfi-0.1.0.dist-info/licenses/LICENSE
kbfi-0.1.0.dist-info/METADATA
kbfi-0.1.0.dist-info/WHEEL
kbfi-0.1.0.dist-info/entry_points.txt
kbfi-0.1.0.dist-info/top_level.txt
kbfi-0.1.0.dist-info/RECORD
