Metadata-Version: 2.4
Name: kbfi
Version: 0.1.0
Summary: A comprehensive WiFi and MAC address scanning toolkit with vendor lookup capabilities
Home-page: https://github.com/itskbagain/kbfi
Author: Kaustubh Bhattacharyya
Author-email: kb01tech@gmail.com
License: MIT
Keywords: wifi,network,scanner,mac-address,vendor-lookup
Classifier: Development Status :: 4 - Beta
Classifier: Intended Audience :: Developers
Classifier: Intended Audience :: System Administrators
Classifier: License :: OSI Approved :: MIT License
Classifier: Operating System :: Microsoft :: Windows
Classifier: Operating System :: POSIX :: Linux
Classifier: Programming Language :: Python :: 3
Classifier: Programming Language :: Python :: 3.8
Classifier: Programming Language :: Python :: 3.9
Classifier: Programming Language :: Python :: 3.10
Classifier: Programming Language :: Python :: 3.11
Classifier: Topic :: System :: Networking
Classifier: Topic :: System :: Systems Administration
Requires-Python: >=3.8
License-File: LICENSE
Requires-Dist: requests>=2.31.0
Dynamic: license-file
